zycspidertool/Spidertool.py
zycspidertool/__init__.py
zyctool-1.1.5.dist-info/METADATA
zyctool-1.1.5.dist-info/WHEEL
zyctool-1.1.5.dist-info/top_level.txt
zyctool-1.1.5.dist-info/RECORD
