Metadata-Version: 2.1
Name: zyctool
Version: 1.1.5
Summary: 爬虫工具库
Author: zyc
Author-email: 1109203201@qq.com
Classifier: Programming Language :: Python :: 3
Classifier: License :: OSI Approved :: MIT License
Classifier: Operating System :: OS Independent
Requires-Python: >=3.6
Requires-Dist: xlrd (==1.2.0)
